pyomeca/__init__.py
pyomeca/_version.py
pyomeca/analogs.py
pyomeca/angles.py
pyomeca/dataarray_accessor.py
pyomeca/markers.py
pyomeca/rototrans.py
pyomeca/io/__init__.py
pyomeca/io/read.py
pyomeca/io/utils.py
pyomeca/io/write.py
pyomeca/processing/__init__.py
pyomeca/processing/angles.py
pyomeca/processing/filter.py
pyomeca/processing/interp.py
pyomeca/processing/markers.py
pyomeca/processing/matrix.py
pyomeca/processing/misc.py
pyomeca/processing/rototrans.py
pyomeca-2024.0.2.dist-info/LICENSE.md
pyomeca-2024.0.2.dist-info/METADATA
pyomeca-2024.0.2.dist-info/WHEEL
pyomeca-2024.0.2.dist-info/top_level.txt
pyomeca-2024.0.2.dist-info/RECORD
