Metadata-Version: 2.1
Name: pyomeca
Version: 2024.0.2
Summary: pyomeca is a python library allowing to carry out a complete biomechanical analysis; in a simple, logical and concise way
Author: Benjamin Michaud
Author-email: Romain Martinez <martinez.staps@gmail.com>
License: Apache 2.0
Project-URL: Repository, https://github.com/pyomeca/pyomeca
Keywords: pyomeca
Requires-Python: >=3.6
License-File: LICENSE.md
Requires-Dist: numpy
Requires-Dist: scipy
Requires-Dist: xarray
Requires-Dist: ezc3d>=1.3.2
Requires-Dist: matplotlib
Requires-Dist: bottleneck
Requires-Dist: openpyxl
